neo4j_database_client/__init__.py
neo4j_database_client/client.py
neo4j_database_client/models.py
neo4j_database_client-0.1.5.dist-info/METADATA
neo4j_database_client-0.1.5.dist-info/WHEEL
neo4j_database_client-0.1.5.dist-info/RECORD
